mcp_client/__init__.py
mcp_client/server.py
mcp_client_tools-0.1.6.dist-info/METADATA
mcp_client_tools-0.1.6.dist-info/WHEEL
mcp_client_tools-0.1.6.dist-info/entry_points.txt
mcp_client_tools-0.1.6.dist-info/top_level.txt
mcp_client_tools-0.1.6.dist-info/RECORD
