Metadata-Version: 2.4
Name: mcp-client-tools
Version: 0.1.6
Summary: Add your description here
Requires-Python: >=3.11
Requires-Dist: async-exit-stack>=1.0.1
Requires-Dist: asyncio>=3.4.3
Requires-Dist: mcp[cli]>=1.6.0
Requires-Dist: openpyxl>=3.1.5
Requires-Dist: pandas>=2.2.3
Requires-Dist: typing>=3.10.0.0
